CHANGELOG.txt
LICENSE.txt
MANIFEST.in
README.rst
setup.cfg
setup.py
tests/objects/__init__.py
zendesk/__init__.py
zendesk/base.py
zendesk/custom_exceptions.py
zendesk/custom_fields.py
zendesk/helper.py
zendesk/organization_memberships.py
zendesk/organizations.py
zendesk/tickets.py
zendesk/users.py
zendesk/objects/__init__.py
zendesk/objects/base.py
zendesk/objects/organization.py
zendesk/objects/organization_membership.py
zendesk/objects/ticket.py
zendesk/objects/user.py
zendesk_integration.egg-info/PKG-INFO
zendesk_integration.egg-info/SOURCES.txt
zendesk_integration.egg-info/dependency_links.txt
zendesk_integration.egg-info/entry_points.txt
zendesk_integration.egg-info/not-zip-safe
zendesk_integration.egg-info/requires.txt
zendesk_integration.egg-info/top_level.txt