Metadata-Version: 1.1
Name: zendesk-integration
Version: 0.2.4
Summary: Communicator with the Zendesk API
Home-page: UNKNOWN
Author: Rafael Portugal
Author-email: rafaelportugal05@gmail.com
License: MIT
Keywords: zendesk api
Platform: UNKNOWN
Classifier: Development Status :: 1 - Planning
Classifier: Programming Language :: Python
